olscheck/__init__.py
olscheck/data_generator.py
olscheck/ols_assumptions_check.py
olscheck/original.py
olscheck-0.1.8.dist-info/METADATA
olscheck-0.1.8.dist-info/WHEEL
olscheck-0.1.8.dist-info/top_level.txt
olscheck-0.1.8.dist-info/RECORD
