Metadata-Version: 2.4
Name: olscheck
Version: 0.1.8
Summary: A library to check OLS assumptions.
Home-page: https://github.com/janrth/olscheck
Author: Jan Rathfelder
Author-email: jan_rathfelder@yahoo.de
Project-URL: Homepage, https://github.com/janrth/olscheck
Requires-Python: >=3.9
Requires-Dist: numpy==1.26.4
Requires-Dist: pandas==2.2.2
Requires-Dist: matplotlib==3.8.4
Requires-Dist: seaborn==0.13.2
Requires-Dist: scikit-learn==1.4.2
Requires-Dist: statsmodels==0.14.2
Requires-Dist: scienceplots==2.1.1
Dynamic: author
Dynamic: author-email
Dynamic: home-page
Dynamic: requires-python
